{"metadata":{},"options":{"assumptions":{},"compact":false,"sourceMaps":true,"ast":true,"babelrc":false,"configFile":false,"parserOpts":{"sourceType":"module","sourceFileName":"C:\\Users\\zianz\\OneDrive\\Documents\\GitHub\\X\\app\\imports\\ui\\components\\Visualize.jsx","plugins":["*","flow","jsx","asyncGenerators","bigInt","classPrivateMethods","classPrivateProperties","classProperties","doExpressions","dynamicImport","exportDefaultFrom","exportExtensions","exportNamespaceFrom","functionBind","functionSent","importMeta","nullishCoalescingOperator","numericSeparator","objectRestSpread","optionalCatchBinding","optionalChaining",["pipelineOperator",{"proposal":"minimal"}],"throwExpressions","classProperties","classPrivateProperties","jsx","nullishCoalescingOperator","nullishCoalescingOperator","optionalChaining","optionalCatchBinding","optionalCatchBinding","classProperties","classPrivateProperties","classPrivateMethods","classProperties","classPrivateProperties","asyncGenerators","asyncGenerators","objectRestSpread","logicalAssignment"],"allowImportExportEverywhere":true,"allowReturnOutsideFunction":true,"allowUndeclaredExports":true,"strictMode":false},"caller":{"name":"meteor","arch":"web.browser"},"sourceFileName":"imports/ui/components/Visualize.jsx","filename":"C:\\Users\\zianz\\OneDrive\\Documents\\GitHub\\X\\app\\imports\\ui\\components\\Visualize.jsx","inputSourceMap":{"version":3,"sources":["imports/ui/components/Visualize.jsx"],"names":["Button","Col","Container","Row","Tab","Tabs","ArrowLeft","ArrowRight","React","ChartType","Refine","Annotate","Layout","Visualize"],"mappings":";;AAAA,SAASA,MAAT,EAAiBC,GAAjB,EAAsBC,SAAtB,EAAiCC,GAAjC,EAAsCC,GAAtC,EAA2CC,IAA3C,QAAuD,iBAAvD;AACA,SAASC,SAAT,EAAoBC,UAApB,QAAsC,uBAAtC;AACA,OAAOC,KAAP,MAAkB,OAAlB;AACA,OAAOC,SAAP,MAAsB,aAAtB;AACA,OAAOC,MAAP,MAAmB,UAAnB;AACA,OAAOC,QAAP,MAAqB,YAArB;AACA,OAAOC,MAAP,MAAmB,UAAnB;;AAEA,MAAMC,SAAS,GAAG,MAChB,CAAC,SAAD,CAAW,UAAU,MAArB,CAA4B;AAC9B,IAAI,CAAC,GAAD,CAAK;AACT,MAAM,CAAC,GAAD,CAAK;AACX,QAAQ,CAAC,IAAD,CACE,iBAAiB,SADnB,CAEE,GAAG,kBAFL,CAGE,UAAU,MAHZ,CAIE,IAJF,CAKC;AACT,UAAU,CAAC,GAAD,CAAK,SAAS,MAAd,CAAqB,MAAM,YAA3B,CAAwC;AAClD,YAAY,CAAC,SAAD,GAAa;AACzB,UAAU,EAAE,GAAF,CAAM;AAChB,UAAU,CAAC,GAAD,CAAK,SAAS,SAAd,CAAwB,MAAM,QAA9B,CAAuC;AACjD,YAAY,CAAC,MAAD,GAAU;AACtB,UAAU,EAAE,GAAF,CAAM;AAChB,UAAU,CAAC,GAAD,CAAK,SAAS,SAAd,CAAwB,MAAM,UAA9B,CAAyC;AACnD,YAAY,CAAC,QAAD,GAAY;AACxB,UAAU,EAAE,GAAF,CAAM;AAChB,UAAU,CAAC,GAAD,CAAK,SAAS,YAAd,CAA2B,MAAM,QAAjC,CAA0C;AACpD,YAAY,CAAC,MAAD,GAAU;AACtB,UAAU,EAAE,GAAF,CAAM;AAChB,QAAQ,EAAE,IAAF,CAAO;AACf,QAAQ,CAAC,MAAD,CAAQ,QAAQ,OAAhB,CAAwB,CAAC,SAAD,GAAa,IAAI,EAAE,MAAF,CAAS;AAC1D,QAAQ,CAAC,MAAD,CAAQ,QAAQ,SAAhB,CAA0B,OAAO,CAAC,UAAD,GAAc,EAAE,MAAF,CAAS;AAChE,MAAM,EAAE,GAAF,CAAM;AACZ,IAAI,EAAE,GAAF,CAAM;AACV,EAAE,EAAE,SAAF,CA3BF;;KAAMA,S;AA6BN,eAAeA,SAAf","sourcesContent":["import { Button, Col, Container, Row, Tab, Tabs } from 'react-bootstrap';\r\nimport { ArrowLeft, ArrowRight } from 'react-bootstrap-icons';\r\nimport React from 'react';\r\nimport ChartType from './ChartType';\r\nimport Refine from './Refine';\r\nimport Annotate from './Annotate';\r\nimport Layout from './Layout';\r\n\r\nconst Visualize = () => (\r\n  <Container className=\"py-3\">\r\n    <Row>\r\n      <Col>\r\n        <Tabs\r\n          defaultActiveKey=\"profile\"\r\n          id=\"fill-tab-example\"\r\n          className=\"mb-3\"\r\n          fill\r\n        >\r\n          <Tab eventKey=\"home\" title=\"Chart type\">\r\n            <ChartType />\r\n          </Tab>\r\n          <Tab eventKey=\"profile\" title=\"Refine\">\r\n            <Refine />\r\n          </Tab>\r\n          <Tab eventKey=\"contact\" title=\"Annotate\">\r\n            <Annotate />\r\n          </Tab>\r\n          <Tab eventKey=\"longer-tab\" title=\"Layout\">\r\n            <Layout />\r\n          </Tab>\r\n        </Tabs>\r\n        <Button variant=\"light\"><ArrowLeft />Back</Button>\r\n        <Button variant=\"primary\">Proceed<ArrowRight /></Button>\r\n      </Col>\r\n    </Row>\r\n  </Container>\r\n);\r\nexport default Visualize;\r\n"]},"targets":{},"cloneInputAst":true,"browserslistConfigFile":false,"passPerPreset":false,"envName":"development","cwd":"C:\\Users\\zianz\\OneDrive\\Documents\\GitHub\\X\\app","root":"C:\\Users\\zianz\\OneDrive\\Documents\\GitHub\\X\\app","rootMode":"root","plugins":[{"key":"base$0","visitor":{"_exploded":true,"_verified":true},"options":{},"externalDependencies":[]},{"key":"base$0$0","visitor":{"Program":{"enter":[null],"exit":[null]},"_exploded":true,"_verified":true},"options":{"avoidModernSyntax":false,"enforceStrictMode":false,"dynamicImport":true,"generateLetDeclarations":true},"externalDependencies":[]},{"key":"transform-runtime","visitor":{"MemberExpression":{"enter":[null]},"ObjectPattern":{"enter":[null]},"BinaryExpression":{"enter":[null]},"_exploded":{},"_verified":{},"Identifier":{"enter":[null]},"JSXIdentifier":{"enter":[null]}},"options":{"version":"7.17.2","helpers":true,"useESModules":false,"corejs":false},"externalDependencies":[]},{"key":"proposal-class-properties","visitor":{"ExportDefaultDeclaration":{"enter":[null]},"_exploded":true,"_verified":true,"ClassExpression":{"enter":[null]},"ClassDeclaration":{"enter":[null]}},"options":{"loose":true},"externalDependencies":[]},{"key":"transform-react-jsx","visitor":{"_exploded":{},"_verified":{},"JSXNamespacedName":{"enter":[null]},"JSXSpreadChild":{"enter":[null]},"Program":{"enter":[null]},"JSXElement":{"exit":[null]},"JSXFragment":{"exit":[null]},"JSXAttribute":{"enter":[null]}},"options":{"pragma":"React.createElement","pragmaFrag":"React.Fragment","runtime":"classic","throwIfNamespace":true,"useBuiltIns":false},"externalDependencies":[]},{"key":"transform-react-display-name","visitor":{"ExportDefaultDeclaration":{"enter":[null]},"CallExpression":{"enter":[null]},"_exploded":true,"_verified":true},"options":{},"externalDependencies":[]},{"key":"transform-react-pure-annotations","visitor":{"CallExpression":{"enter":[null]},"_exploded":true,"_verified":true},"options":{},"externalDependencies":[]},{"key":"syntax-nullish-coalescing-operator","visitor":{"_exploded":true,"_verified":true},"options":{},"externalDependencies":[]},{"key":"proposal-nullish-coalescing-operator","visitor":{"_exploded":{},"_verified":{},"LogicalExpression":{"enter":[null]}},"options":{},"externalDependencies":[]},{"key":"syntax-optional-chaining","visitor":{"_exploded":true,"_verified":true},"options":{},"externalDependencies":[]},{"key":"proposal-optional-chaining","visitor":{"_exploded":true,"OptionalCallExpression":{"enter":[null]},"OptionalMemberExpression":{"enter":[null]},"_verified":true},"options":{},"externalDependencies":[]},{"key":"syntax-optional-catch-binding","visitor":{"_exploded":true,"_verified":true},"options":{},"externalDependencies":[]},{"key":"proposal-optional-catch-binding","visitor":{"_exploded":{},"_verified":{},"CatchClause":{"enter":[null]}},"options":{},"externalDependencies":[]},{"key":"syntax-class-properties","visitor":{"_exploded":true,"_verified":true},"options":{},"externalDependencies":[]},{"key":"proposal-class-properties","visitor":{"ExportDefaultDeclaration":{"enter":[null]},"_exploded":true,"_verified":true,"ClassExpression":{"enter":[null]},"ClassDeclaration":{"enter":[null]}},"options":{},"externalDependencies":[]},{"key":"syntax-async-generators","visitor":{"_exploded":true,"_verified":true},"options":{},"externalDependencies":[]},{"key":"proposal-async-generator-functions","visitor":{"_exploded":{},"_verified":{},"Program":{"enter":[null]}},"options":{},"externalDependencies":[]},{"key":"syntax-object-rest-spread","visitor":{"_exploded":true,"_verified":true},"options":{},"externalDependencies":[]},{"key":"proposal-object-rest-spread","visitor":{"VariableDeclarator":{"enter":[null]},"ExportNamedDeclaration":{"enter":[null]},"CatchClause":{"enter":[null]},"AssignmentExpression":{"enter":[null]},"ArrayPattern":{"enter":[null]},"ObjectExpression":{"enter":[null]},"_exploded":true,"_verified":true,"FunctionDeclaration":{"enter":[null]},"FunctionExpression":{"enter":[null]},"ObjectMethod":{"enter":[null]},"ArrowFunctionExpression":{"enter":[null]},"ClassMethod":{"enter":[null]},"ClassPrivateMethod":{"enter":[null]},"ForInStatement":{"enter":[null]},"ForOfStatement":{"enter":[null]}},"options":{},"externalDependencies":[]},{"key":"proposal-logical-assignment-operators","visitor":{"_exploded":{},"_verified":{},"AssignmentExpression":{"enter":[null]}},"options":{},"externalDependencies":[]},{"key":"transform-literals","visitor":{"NumericLiteral":{"enter":[null]},"StringLiteral":{"enter":[null]},"_exploded":true,"_verified":true},"options":{},"externalDependencies":[]},{"key":"transform-template-literals","visitor":{"TaggedTemplateExpression":{"enter":[null]},"TemplateLiteral":{"enter":[null]},"_exploded":true,"_verified":true},"options":{},"externalDependencies":[]},{"key":"transform-parameters","visitor":{"_exploded":true,"_verified":true,"FunctionDeclaration":{"enter":[null]},"FunctionExpression":{"enter":[null]},"ObjectMethod":{"enter":[null]},"ArrowFunctionExpression":{"enter":[null]},"ClassMethod":{"enter":[null]},"ClassPrivateMethod":{"enter":[null]}},"options":{},"externalDependencies":[]},{"key":"transform-exponentiation-operator","visitor":{"AssignmentExpression":{"enter":[null]},"BinaryExpression":{"enter":[null]},"_exploded":true,"_verified":true},"options":{},"externalDependencies":[]}],"presets":[],"generatorOpts":{"filename":"C:\\Users\\zianz\\OneDrive\\Documents\\GitHub\\X\\app\\imports\\ui\\components\\Visualize.jsx","comments":true,"compact":false,"sourceMaps":true,"sourceFileName":"imports/ui/components/Visualize.jsx"}},"code":"!function (module1) {\n  let Button, Col, Container, Row, Tab, Tabs;\n  module1.link(\"react-bootstrap\", {\n    Button(v) {\n      Button = v;\n    },\n\n    Col(v) {\n      Col = v;\n    },\n\n    Container(v) {\n      Container = v;\n    },\n\n    Row(v) {\n      Row = v;\n    },\n\n    Tab(v) {\n      Tab = v;\n    },\n\n    Tabs(v) {\n      Tabs = v;\n    }\n\n  }, 0);\n  let ArrowLeft, ArrowRight;\n  module1.link(\"react-bootstrap-icons\", {\n    ArrowLeft(v) {\n      ArrowLeft = v;\n    },\n\n    ArrowRight(v) {\n      ArrowRight = v;\n    }\n\n  }, 1);\n  let React;\n  module1.link(\"react\", {\n    default(v) {\n      React = v;\n    }\n\n  }, 2);\n  let ChartType;\n  module1.link(\"./ChartType\", {\n    default(v) {\n      ChartType = v;\n    }\n\n  }, 3);\n  let Refine;\n  module1.link(\"./Refine\", {\n    default(v) {\n      Refine = v;\n    }\n\n  }, 4);\n  let Annotate;\n  module1.link(\"./Annotate\", {\n    default(v) {\n      Annotate = v;\n    }\n\n  }, 5);\n  let Layout;\n  module1.link(\"./Layout\", {\n    default(v) {\n      Layout = v;\n    }\n\n  }, 6);\n\n  ___INIT_METEOR_FAST_REFRESH(module);\n\n  const Visualize = () => /*#__PURE__*/React.createElement(Container, {\n    className: \"py-3\"\n  }, /*#__PURE__*/React.createElement(Row, null, /*#__PURE__*/React.createElement(Col, null, /*#__PURE__*/React.createElement(Tabs, {\n    defaultActiveKey: \"profile\",\n    id: \"fill-tab-example\",\n    className: \"mb-3\",\n    fill: true\n  }, /*#__PURE__*/React.createElement(Tab, {\n    eventKey: \"home\",\n    title: \"Chart type\"\n  }, /*#__PURE__*/React.createElement(ChartType, null)), /*#__PURE__*/React.createElement(Tab, {\n    eventKey: \"profile\",\n    title: \"Refine\"\n  }, /*#__PURE__*/React.createElement(Refine, null)), /*#__PURE__*/React.createElement(Tab, {\n    eventKey: \"contact\",\n    title: \"Annotate\"\n  }, /*#__PURE__*/React.createElement(Annotate, null)), /*#__PURE__*/React.createElement(Tab, {\n    eventKey: \"longer-tab\",\n    title: \"Layout\"\n  }, /*#__PURE__*/React.createElement(Layout, null))), /*#__PURE__*/React.createElement(Button, {\n    variant: \"light\"\n  }, /*#__PURE__*/React.createElement(ArrowLeft, null), \"Back\"), /*#__PURE__*/React.createElement(Button, {\n    variant: \"primary\"\n  }, \"Proceed\", /*#__PURE__*/React.createElement(ArrowRight, null)))));\n\n  _c = Visualize;\n  module1.exportDefault(Visualize);\n\n  var _c;\n\n  $RefreshReg$(_c, \"Visualize\");\n}.call(this, module);","map":{"version":3,"mappings":";;;;;;;;;;;;;;;;;;;;;;;;;;;;;;;;;;;;;;;;;;;;;;;;;;;;;;;;;;;;;;;;;;;;;;;;;;;;;AAQA,QAAMA,SAAS,GAAG,mBAChB,oBAAC,SAAD;AAAW,eAAU;AAArB,kBACE,oBAAC,GAAD,qBACE,oBAAC,GAAD,qBACE,oBAAC,IAAD;AACE,sBAAiB,SADnB;AAEE,QAAG,kBAFL;AAGE,eAAU,MAHZ;AAIE,QAJF;AAAA,kBAME,oBAAC,GAAD;AAAK,cAAS,MAAd;AAAqB,WAAM;AAA3B,kBACE,oBAAC,SAAD,OADF,CANF,eASE,oBAAC,GAAD;AAAK,cAAS,SAAd;AAAwB,WAAM;AAA9B,kBACE,oBAAC,MAAD,OADF,CATF,eAYE,oBAAC,GAAD;AAAK,cAAS,SAAd;AAAwB,WAAM;AAA9B,kBACE,oBAAC,QAAD,OADF,CAZF,eAeE,oBAAC,GAAD;AAAK,cAAS,YAAd;AAA2B,WAAM;AAAjC,kBACE,oBAAC,MAAD,OADF,CAfF,CADF,eAoBE,oBAAC,MAAD;AAAQ,aAAQ;AAAhB,kBAAwB,oBAAC,SAAD,OAAxB,SApBF,eAqBE,oBAAC,MAAD;AAAQ,aAAQ;AAAhB,6BAAiC,oBAAC,UAAD,OAAjC,CArBF,CADF,CADF,CADF;;OAAMA;wBA6BSA","names":["Visualize"],"sources":["imports/ui/components/Visualize.jsx"],"sourcesContent":["import { Button, Col, Container, Row, Tab, Tabs } from 'react-bootstrap';\r\nimport { ArrowLeft, ArrowRight } from 'react-bootstrap-icons';\r\nimport React from 'react';\r\nimport ChartType from './ChartType';\r\nimport Refine from './Refine';\r\nimport Annotate from './Annotate';\r\nimport Layout from './Layout';\r\n\r\nconst Visualize = () => (\r\n  <Container className=\"py-3\">\r\n    <Row>\r\n      <Col>\r\n        <Tabs\r\n          defaultActiveKey=\"profile\"\r\n          id=\"fill-tab-example\"\r\n          className=\"mb-3\"\r\n          fill\r\n        >\r\n          <Tab eventKey=\"home\" title=\"Chart type\">\r\n            <ChartType />\r\n          </Tab>\r\n          <Tab eventKey=\"profile\" title=\"Refine\">\r\n            <Refine />\r\n          </Tab>\r\n          <Tab eventKey=\"contact\" title=\"Annotate\">\r\n            <Annotate />\r\n          </Tab>\r\n          <Tab eventKey=\"longer-tab\" title=\"Layout\">\r\n            <Layout />\r\n          </Tab>\r\n        </Tabs>\r\n        <Button variant=\"light\"><ArrowLeft />Back</Button>\r\n        <Button variant=\"primary\">Proceed<ArrowRight /></Button>\r\n      </Col>\r\n    </Row>\r\n  </Container>\r\n);\r\nexport default Visualize;\r\n"]},"sourceType":"module","externalDependencies":{},"hash":"65069ebb68ea3235205554d6c43ca9f116f22d3e"}
